Metadata-Version: 2.1
Name: 2us
Version: 0.0.1
Summary: Glueing functionals with __.
Home-page: https://github.com/strongrex2001/__
Author: flandre.info
Author-email: flandre@scarletx.cn
License: UNKNOWN
Platform: UNKNOWN
Classifier: Programming Language :: Python :: 3 :: Only
Classifier: License :: OSI Approved :: Apache Software License
Classifier: Operating System :: OS Independent
Requires-Python: ~=3.5
